appliapps/__init__.py
appliapps/examples/__init__.py
appliapps/examples/copyworkflow.py
appliapps/examples/cp.py
appliapps/examples/echobasic.py
appliapps/examples/echowrapped.py
appliapps/examples/meta.py
appliapps/examples/sort.py
appliapps/examples/template.py
appliapps/flow/__init__.py
appliapps/flow/branch.py
appliapps/flow/collate.py
appliapps/flow/jobid.py
appliapps/flow/merge.py
appliapps/flow/mergetoline.py
appliapps/flow/split.py
applicake/__init__.py
applicake/apl.py
applicake/base/__init__.py
applicake/base/app.py
applicake/base/apputils/__init__.py
applicake/base/apputils/dicts.py
applicake/base/apputils/dirs.py
applicake/base/apputils/dropbox.py
applicake/base/apputils/dynrun.py
applicake/base/apputils/templates.py
applicake/base/apputils/validation.py
applicake/base/coreutils/__init__.py
applicake/base/coreutils/arguments.py
applicake/base/coreutils/info.py
applicake/base/coreutils/keys.py
applicake/base/coreutils/log.py
applicake-0.0.28.dist-info/METADATA
applicake-0.0.28.dist-info/WHEEL
applicake-0.0.28.dist-info/entry_points.txt
applicake-0.0.28.dist-info/top_level.txt
applicake-0.0.28.dist-info/RECORD
